simpleoptions/__init__.py
simpleoptions/environment.py
simpleoptions/option.py
simpleoptions/options_agent.py
simpleoptions/primitive_option.py
simpleoptions/function_approximation/__init__.py
simpleoptions/function_approximation/environment.py
simpleoptions/function_approximation/primitive_option.py
simpleoptions/implementations/__init__.py
simpleoptions/implementations/betweenness.py
simpleoptions/implementations/diffusion_options.py
simpleoptions/implementations/eigenoptions.py
simpleoptions/implementations/generic_option_generator.py
simpleoptions/implementations/subgoal_option_generator.py
simpleoptions/utils/__init__.py
simpleoptions/utils/math.py
simpleoptions-0.9.1.dist-info/LICENSE
simpleoptions-0.9.1.dist-info/METADATA
simpleoptions-0.9.1.dist-info/WHEEL
simpleoptions-0.9.1.dist-info/top_level.txt
simpleoptions-0.9.1.dist-info/RECORD
