Metadata-Version: 2.1
Name: simpleoptions
Version: 0.9.1
Summary: A simple and flexible framework for working with Options in Reinforcement Learning.
Home-page: https://github.com/Ueva/BaRL-SimpleOptions
Author: Joshua Evans
Author-email: jbe25@bath.ac.uk
Classifier: Programming Language :: Python :: 3
Classifier: License :: OSI Approved :: MIT License
Classifier: Operating System :: OS Independent
Classifier: Intended Audience :: Science/Research
Classifier: Topic :: Scientific/Engineering :: Artificial Intelligence
Classifier: Natural Language :: English
Requires-Python: >=3.8
License-File: LICENSE
Requires-Dist: numpy
Requires-Dist: networkx
Requires-Dist: gymnasium
